exposepy/__init__.py
exposepy-0.1.1.dist-info/METADATA
exposepy-0.1.1.dist-info/WHEEL
exposepy-0.1.1.dist-info/licenses/LICENSE
exposepy-0.1.1.dist-info/RECORD
