Metadata-Version: 2.4
Name: exposepy
Version: 0.1.1
Summary: Minimalist decorator for exposing public APIs
Project-URL: Homepage, https://github.com/yourusername/exposepy
Author-email: Daniel Estevez <kemossabee@gmail.com>
License-Expression: MIT
License-File: LICENSE
Classifier: Development Status :: 4 - Beta
Classifier: Intended Audience :: Developers
Classifier: License :: OSI Approved :: MIT License
Classifier: Programming Language :: Python :: 3
Classifier: Programming Language :: Python :: 3.8
Classifier: Programming Language :: Python :: 3.9
Classifier: Programming Language :: Python :: 3.10
Classifier: Programming Language :: Python :: 3.11
Classifier: Programming Language :: Python :: 3.12
Requires-Python: >=3.8
